{
    "$schema": "http://json-schema.org/draft-04/schema#",
    "title": "MyField",
    "description": "MyField Description",
    "type": "object",
    "properties": {
        "rendered": {
            "type": "object",
            "properties": {
                "boolean-value": {
                    "type": "boolean"
                },
                "items": {
                    "$ref": "#/definitions/items"
                }
            }
        }
    },
    "required": [],
    "additionalProperties": true,

    "definitions": {
        "items": {
            "$schema": "http://json-schema.org/draft-04/schema#",
            "title": "fms-field-items",
            "description": "Fms Field Items Description",
            "type": "object",
            "properties": {
                "func": {
                    "type": "string"
                },
                "list": {
                    "type": "array",
                    "items": {
                        "type": "object",
                        "properties": {

                        }
                    }
                },
                "ref": {
                    "type": "object",
                    "properties": {
                        "db": {
                            "type": "string"
                        },
                        "itemTable": {
                            "type": "string"
                        },
                        "query": {
                            "type": "object",
                            "properties": {
                                "func": {
                                    "type": "string"
                                },
                                "list": {
                                    "type": "array",
                                    "items": {
                                        "type": "object",
                                        "properties": {
                                            "key": {
                                                "type": "string"
                                            },
                                            "string-value": {
                                                "type": "string"
                                            }
                                        },
                                        "additionalProperties": false                                        
                                    }
                                }
                            }
                        },
                        "adminQuery": {
                            "type": "object",
                            "properties": {
                                "func": {
                                    "type": "string"
                                },
                                "list": {
                                    "type": "array",
                                    "items": {
                                        "type": "object",
                                        "properties": {
                                            "key": {
                                                "type": "string"
                                            },
                                            "string-value": {
                                                "type": "string"
                                            }
                                        },
                                        "additionalProperties": false                                        
                                    }
                                }
                            }
                        },
                        "historyQuery": {
                            "type": "object",
                            "properties": {
                                "func": {
                                    "type": "string"
                                },
                                "list": {
                                    "type": "array",
                                    "items": {
                                        "type": "object",
                                        "properties": {
                                            "key": {
                                                "type": "string"
                                            },
                                            "string-value": {
                                                "type": "string"
                                            }
                                        },
                                        "additionalProperties": false                                        
                                    }
                                }
                            }
                        },
                        "v": {
                            "type": "array",
                            "items": {
                                "type": "object"
                            }
                        },
                        "sort": {
                            "type": "object"
                        }
                    },
                    "additionalProperties": false                                        
                }
            },
            "required": [],
            "additionalProperties": false    
        }
    }
}
